pail/__init__.py
pail/augmented_anomlay.py
pail/change_color.py
pail/cutpaste.py
pail/fractal_aug.py
pail/hard_augment_cutpaste.py
pail/mem_seg_perlin.py
pail/pai.py
pail/perlin.py
pail/rand_aug_cut_paste.py
pail/random_pert.py
pail/seg_model.py
pail/simplex_noise.py
pai_lib-1.0.0.1.dist-info/LICENSE.txt
pai_lib-1.0.0.1.dist-info/METADATA
pai_lib-1.0.0.1.dist-info/WHEEL
pai_lib-1.0.0.1.dist-info/top_level.txt
pai_lib-1.0.0.1.dist-info/RECORD
