Metadata-Version: 2.1
Name: pai_lib
Version: 1.0.0.1
Summary: Visual Pseudo Anomaly Insertion Library for creating a Pseudo Anomaly Dataset.
Author-email: Rizwan Ali Shah <rizwanaliqau@gmail.com>
License: MIT
License-File: LICENSE.txt
Requires-Dist: torchvision ==0.18.1
Requires-Dist: albumentations ==1.4.11
Requires-Dist: numpy >=1.24.2
Requires-Dist: scipy >=1.10.1
Requires-Dist: opencv-python ==4.10.0.84
Requires-Dist: patchify ==0.2.3
Requires-Dist: pillow ==10.2.0
Requires-Dist: opensimplex ==0.4.5.1
Requires-Dist: noise ==1.2.2
Requires-Dist: imgaug ==0.4.0
Requires-Dist: einops ==0.8.0
